AUTHORS
LICENSE
MANIFEST.in
README.md
pngcanvas.py
reference.png
setup.py
setuputils.py
test_pngcanvas.py
pngcanvas.egg-info/PKG-INFO
pngcanvas.egg-info/SOURCES.txt
pngcanvas.egg-info/dependency_links.txt
pngcanvas.egg-info/top_level.txt