Metadata-Version: 1.1
Name: pngcanvas
Version: 1.0.3
Summary: A minimalist library to render PNG images using pure Python.
Home-page: https://github.com/rcarmo/pngcanvas
Author: Rui Carmo
Author-email: rcarmo@gmail.com
License: MIT
Platform: UNKNOWN
Classifier: Programming Language :: Python :: 2
Classifier: Programming Language :: Python :: 2.6
Classifier: Programming Language :: Python :: 2.7
Classifier: Programming Language :: Python :: 3
Classifier: Programming Language :: Python :: 3.2
Classifier: Programming Language :: Python :: 3.3
Classifier: License :: OSI Approved :: MIT License
